aptible/__init__.py
aptible/api/__init__.py
aptible/api/config.py
aptible/api/error.py
aptible/api/manager/__init__.py
aptible/api/manager/api_manager.py
aptible/api/manager/aptible_api.py
aptible/api/manager/aptible_auth_api.py
aptible/api/manager/empty_response.py
aptible/api/manager/url_util.py
aptible/api/model/__init__.py
aptible/api/model/empty_resource.py
aptible/api/model/resource.py
aptible_api-0.4.0.dist-info/LICENCE.md
aptible_api-0.4.0.dist-info/METADATA
aptible_api-0.4.0.dist-info/WHEEL
aptible_api-0.4.0.dist-info/top_level.txt
aptible_api-0.4.0.dist-info/RECORD
