Metadata-Version: 2.1
Name: aptible-api
Version: 0.4.0
Summary: Object Oriented interface for Aptible API
Home-page: https://github.com/TrialSpark/aptible-api
Author: Zachary Elliott
Author-email: zellio@trialspark.com
License: UNKNOWN
Project-URL: Bug Tracker, https://github.com/TrialSpark/aptible-api
Platform: UNKNOWN
Classifier: Programming Language :: Python :: 3
Classifier: License :: OSI Approved :: MIT License
Classifier: Operating System :: OS Independent
Requires-Python: >=3.6
License-File: LICENCE.md
Requires-Dist: PyYAML (>=5.4)
Requires-Dist: inflection (>=0.5)
Requires-Dist: requests (>=2.25)
